AUTHORS.rst
CONTRIBUTING.rst
HISTORY.rst
LICENSE
MANIFEST.in
README.rst
setup.cfg
setup.py
docs/Makefile
docs/authors.rst
docs/conf.py
docs/contributing.rst
docs/history.rst
docs/index.rst
docs/installation.rst
docs/make.bat
docs/readme.rst
docs/usage.rst
send_clowder/__init__.py
send_clowder/send_clowder.py
send_clowder.egg-info/PKG-INFO
send_clowder.egg-info/SOURCES.txt
send_clowder.egg-info/dependency_links.txt
send_clowder.egg-info/entry_points.txt
send_clowder.egg-info/not-zip-safe
send_clowder.egg-info/requires.txt
send_clowder.egg-info/top_level.txt
tests/__init__.py
tests/test_send_clowder.py