Metadata-Version: 1.1
Name: send-clowder
Version: 0.1.1
Summary: Simple command-line tool for sending messages to clowder
Home-page: https://github.com/etscrivner/send_clowder
Author: Eric Scrivner
Author-email: eric.t.scrivner@gmail.com
License: BSD
Keywords: send_clowder
Platform: UNKNOWN
Classifier: Development Status :: 2 - Pre-Alpha
Classifier: Intended Audience :: Developers
Classifier: License :: OSI Approved :: BSD License
Classifier: Natural Language :: English
Classifier: Programming Language :: Python :: 2
Classifier: Programming Language :: Python :: 2.6
Classifier: Programming Language :: Python :: 2.7
Classifier: Programming Language :: Python :: 3
Classifier: Programming Language :: Python :: 3.3
Classifier: Programming Language :: Python :: 3.4
